LICENSE
MANIFEST.in
README.rst
setup.py
tmblr.py
doc/tmblr.1
tmblr.egg-info/PKG-INFO
tmblr.egg-info/SOURCES.txt
tmblr.egg-info/dependency_links.txt
tmblr.egg-info/entry_points.txt
tmblr.egg-info/requires.txt
tmblr.egg-info/top_level.txt