Metadata-Version: 1.1
Name: tmblr
Version: 2015.12.4
Summary: a silly tumblr client
Home-page: http://kyber.io/tmblr
Author: bie
Author-email: bie@kyber.io
License: MIT
Keywords: tumblr blog
Platform: UNKNOWN
Classifier: Development Status :: 3 - Alpha
Classifier: Environment :: Console
Classifier: Topic :: Internet :: WWW/HTTP
Classifier: License :: OSI Approved :: MIT License
Classifier: Programming Language :: Python :: 2.7
Classifier: Operating System :: POSIX
Classifier: Operating System :: POSIX :: Linux
